setup.py
alert_grid/__init__.py
alert_grid/base.py
alert_grid/exceptions.py
alert_grid.egg-info/PKG-INFO
alert_grid.egg-info/SOURCES.txt
alert_grid.egg-info/dependency_links.txt
alert_grid.egg-info/not-zip-safe
alert_grid.egg-info/top_level.txt