Metadata-Version: 1.0
Name: alert-grid
Version: 1.0.0
Summary: Alert Grid utility
Home-page: http://github.com/ojii/alert-grid
Author: Jonas Obrist
Author-email: jonas.obrist@divio.ch
License: UNKNOWN
Platform: UNKNOWN
